pytest_simple_settings/__init__.py
pytest_simple_settings/_plugin.py
pytest_simple_settings-0.1.5.dist-info/LICENSE
pytest_simple_settings-0.1.5.dist-info/METADATA
pytest_simple_settings-0.1.5.dist-info/WHEEL
pytest_simple_settings-0.1.5.dist-info/entry_points.txt
pytest_simple_settings-0.1.5.dist-info/top_level.txt
pytest_simple_settings-0.1.5.dist-info/RECORD
