Metadata-Version: 2.1
Name: pytest-simple-settings
Version: 0.1.5
Summary: simple-settings plugin for pytest
Home-page: https://github.com/tkukushkin/pytest-simple-settings
Author: Timofey Kukushkin
Author-email: tima@kukushkin.me
License: MIT
Project-URL: Source, https://github.com/tkukushkin/pytest-simple-settings
Platform: UNKNOWN
Classifier: Development Status :: 4 - Beta
Classifier: Environment :: Plugins
Classifier: Framework :: Pytest
Classifier: Intended Audience :: Developers
Classifier: License :: OSI Approved :: MIT License
Classifier: Operating System :: OS Independent
Classifier: Programming Language :: Python :: 2
Classifier: Programming Language :: Python :: 2.7
Classifier: Programming Language :: Python :: 3
Classifier: Programming Language :: Python :: 3.6
Classifier: Programming Language :: Python :: 3.7
Classifier: Programming Language :: Python :: 3.8
Classifier: Programming Language :: Python :: 3.9
Classifier: Topic :: Software Development :: Libraries :: Python Modules
Classifier: Topic :: Software Development :: Testing :: Mocking
Requires-Dist: pytest
Requires-Dist: simple-settings
Requires-Dist: typing ; python_version < "3"
Provides-Extra: test
Requires-Dist: pycodestyle ; extra == 'test'
Requires-Dist: pylint ; extra == 'test'
